{
  "node_modules/@sveltejs/kit/src/runtime/client/start.js": {
    "file": "_app/immutable/start-fdc84e5e.js",
    "src": "node_modules/@sveltejs/kit/src/runtime/client/start.js",
    "isEntry": true,
    "imports": [
      "_index-1a2b90b6.js"
    ],
    "dynamicImports": [
      ".svelte-kit/generated/nodes/0.js",
      ".svelte-kit/generated/nodes/1.js",
      ".svelte-kit/generated/nodes/2.js",
      ".svelte-kit/generated/nodes/3.js",
      ".svelte-kit/generated/nodes/4.js",
      ".svelte-kit/generated/nodes/5.js",
      ".svelte-kit/generated/nodes/6.js"
    ]
  },
  "src/routes/+layout.svelte": {
    "file": "_app/immutable/components/pages/_layout.svelte-cdf88fe9.js",
    "src": "src/routes/+layout.svelte",
    "isEntry": true,
    "imports": [
      "_index-1a2b90b6.js"
    ],
    "css": [
      "_app/immutable/assets/+layout-bd17d1e8.css"
    ]
  },
  "node_modules/@sveltejs/kit/src/runtime/components/error.svelte": {
    "file": "_app/immutable/components/error.svelte-5b2d98f1.js",
    "src": "node_modules/@sveltejs/kit/src/runtime/components/error.svelte",
    "isEntry": true,
    "imports": [
      "_index-1a2b90b6.js",
      "_stores-6cc6c2f0.js"
    ]
  },
  "src/routes/+page.svelte": {
    "file": "_app/immutable/components/pages/_page.svelte-ee3c4fc2.js",
    "src": "src/routes/+page.svelte",
    "isEntry": true,
    "imports": [
      "_index-1a2b90b6.js",
      "_utils-688bd5b5.js"
    ],
    "css": [
      "_app/immutable/assets/+page-3d13de9c.css"
    ]
  },
  "src/routes/example/one-way/+page.svelte": {
    "file": "_app/immutable/components/pages/example/one-way/_page.svelte-62e27ca1.js",
    "src": "src/routes/example/one-way/+page.svelte",
    "isEntry": true,
    "imports": [
      "_index-1a2b90b6.js"
    ]
  },
  "src/routes/example/one-way-live/+page.svelte": {
    "file": "_app/immutable/components/pages/example/one-way-live/_page.svelte-b8f72dcf.js",
    "src": "src/routes/example/one-way-live/+page.svelte",
    "isEntry": true,
    "imports": [
      "_index-1a2b90b6.js"
    ]
  },
  "src/routes/example/round-trip/+page.svelte": {
    "file": "_app/immutable/components/pages/example/round-trip/_page.svelte-154db505.js",
    "src": "src/routes/example/round-trip/+page.svelte",
    "isEntry": true,
    "imports": [
      "_index-1a2b90b6.js"
    ]
  },
  "src/routes/partner/[partner]/+page.svelte": {
    "file": "_app/immutable/components/pages/partner/_partner_/_page.svelte-c7f4b41f.js",
    "src": "src/routes/partner/[partner]/+page.svelte",
    "isEntry": true,
    "imports": [
      "_index-1a2b90b6.js",
      "_stores-6cc6c2f0.js",
      "_utils-688bd5b5.js"
    ],
    "css": [
      "_app/immutable/assets/+page-eee9b4e7.css"
    ]
  },
  "_index-1a2b90b6.js": {
    "file": "_app/immutable/chunks/index-1a2b90b6.js"
  },
  "_stores-6cc6c2f0.js": {
    "file": "_app/immutable/chunks/stores-6cc6c2f0.js",
    "imports": [
      "_index-1a2b90b6.js"
    ]
  },
  "_utils-688bd5b5.js": {
    "file": "_app/immutable/chunks/utils-688bd5b5.js"
  },
  ".svelte-kit/generated/nodes/0.js": {
    "file": "_app/immutable/chunks/0-fc86d3a6.js",
    "src": ".svelte-kit/generated/nodes/0.js",
    "isDynamicEntry": true,
    "imports": [
      "src/routes/+layout.svelte",
      "_index-1a2b90b6.js"
    ]
  },
  ".svelte-kit/generated/nodes/1.js": {
    "file": "_app/immutable/chunks/1-174b1b91.js",
    "src": ".svelte-kit/generated/nodes/1.js",
    "isDynamicEntry": true,
    "imports": [
      "node_modules/@sveltejs/kit/src/runtime/components/error.svelte",
      "_index-1a2b90b6.js",
      "_stores-6cc6c2f0.js"
    ]
  },
  ".svelte-kit/generated/nodes/2.js": {
    "file": "_app/immutable/chunks/2-bb0a9cfe.js",
    "src": ".svelte-kit/generated/nodes/2.js",
    "isDynamicEntry": true,
    "imports": [
      "src/routes/+page.svelte",
      "_index-1a2b90b6.js",
      "_utils-688bd5b5.js"
    ]
  },
  ".svelte-kit/generated/nodes/3.js": {
    "file": "_app/immutable/chunks/3-e921488b.js",
    "src": ".svelte-kit/generated/nodes/3.js",
    "isDynamicEntry": true,
    "imports": [
      "src/routes/example/one-way/+page.svelte",
      "_index-1a2b90b6.js"
    ]
  },
  ".svelte-kit/generated/nodes/4.js": {
    "file": "_app/immutable/chunks/4-6446c0a3.js",
    "src": ".svelte-kit/generated/nodes/4.js",
    "isDynamicEntry": true,
    "imports": [
      "src/routes/example/one-way-live/+page.svelte",
      "_index-1a2b90b6.js"
    ]
  },
  ".svelte-kit/generated/nodes/5.js": {
    "file": "_app/immutable/chunks/5-24182e2b.js",
    "src": ".svelte-kit/generated/nodes/5.js",
    "isDynamicEntry": true,
    "imports": [
      "src/routes/example/round-trip/+page.svelte",
      "_index-1a2b90b6.js"
    ]
  },
  ".svelte-kit/generated/nodes/6.js": {
    "file": "_app/immutable/chunks/6-70883d42.js",
    "src": ".svelte-kit/generated/nodes/6.js",
    "isDynamicEntry": true,
    "imports": [
      "src/routes/partner/[partner]/+page.svelte",
      "_index-1a2b90b6.js",
      "_stores-6cc6c2f0.js",
      "_utils-688bd5b5.js"
    ]
  },
  "src/routes/+page.css": {
    "file": "_app/immutable/assets/+page-3d13de9c.css",
    "src": "src/routes/+page.css"
  },
  "src/routes/partner/[partner]/+page.css": {
    "file": "_app/immutable/assets/+page-eee9b4e7.css",
    "src": "src/routes/partner/[partner]/+page.css"
  },
  "src/routes/+layout.css": {
    "file": "_app/immutable/assets/+layout-bd17d1e8.css",
    "src": "src/routes/+layout.css"
  }
}